spark_on_k8s/__init__.py
spark_on_k8s/airflow/__init__.py
spark_on_k8s/airflow/operator_links.py
spark_on_k8s/airflow/operators.py
spark_on_k8s/airflow/provider_info.py
spark_on_k8s/airflow/scripts/__init__.py
spark_on_k8s/airflow/scripts/spark_sql.py
spark_on_k8s/airflow/triggers.py
spark_on_k8s/api/__init__.py
spark_on_k8s/api/app.py
spark_on_k8s/api/apps.py
spark_on_k8s/api/configuration.py
spark_on_k8s/api/main.py
spark_on_k8s/api/utils.py
spark_on_k8s/api/webserver/__init__.py
spark_on_k8s/api/webserver/static/app_logs.css
spark_on_k8s/api/webserver/static/apps.css
spark_on_k8s/api/webserver/templates/app_logs.html
spark_on_k8s/api/webserver/templates/apps.html
spark_on_k8s/api/webserver/templates/error.html
spark_on_k8s/cli/__init__.py
spark_on_k8s/cli/api.py
spark_on_k8s/cli/app.py
spark_on_k8s/cli/apps.py
spark_on_k8s/cli/namespace.py
spark_on_k8s/cli/options.py
spark_on_k8s/client.py
spark_on_k8s/k8s/__init__.py
spark_on_k8s/k8s/async_client.py
spark_on_k8s/k8s/sync_client.py
spark_on_k8s/utils/__init__.py
spark_on_k8s/utils/app_manager.py
spark_on_k8s/utils/async_app_manager.py
spark_on_k8s/utils/configuration.py
spark_on_k8s/utils/logging_mixin.py
spark_on_k8s/utils/setup_namespace.py
spark_on_k8s/utils/spark_app_status.py
spark_on_k8s/utils/types.py
spark_on_k8s/utils/warnings.py
spark_on_k8s-0.12.1.dist-info/LICENSE
spark_on_k8s-0.12.1.dist-info/METADATA
spark_on_k8s-0.12.1.dist-info/WHEEL
spark_on_k8s-0.12.1.dist-info/entry_points.txt
spark_on_k8s-0.12.1.dist-info/RECORD
