Metadata-Version: 2.3
Name: spark-on-k8s
Version: 0.12.1
Summary: A Python package to submit and manage Apache Spark applications on Kubernetes.
License: Apache-2.0
Keywords: spark,kubernetes,k8s,spark-submit,spark-on-k8s
Author: Hussein Awala
Author-email: hussein@awala.fr
Requires-Python: >=3.9,<4.0
Classifier: License :: OSI Approved :: Apache Software License
Classifier: Programming Language :: Python :: 3
Classifier: Programming Language :: Python :: 3.9
Classifier: Programming Language :: Python :: 3.10
Classifier: Programming Language :: Python :: 3.11
Classifier: Programming Language :: Python :: 3.12
Classifier: Programming Language :: Python :: 3.13
Provides-Extra: airflow
Provides-Extra: api
Requires-Dist: StrEnum (>=0.4.15,<0.5.0) ; python_version < "3.11"
Requires-Dist: aiohttp (>=3.10.2) ; extra == "api"
Requires-Dist: apache-airflow (>=2.6.0) ; (python_version < "3.13") and (extra == "airflow")
Requires-Dist: apache-airflow-providers-cncf-kubernetes (>=7.0.0) ; (python_version < "3.13") and (extra == "airflow")
Requires-Dist: click (>=8.0.1,<9.0.0)
Requires-Dist: eval-type-backport (>=0.2.0,<0.3.0) ; python_version == "3.9"
Requires-Dist: fastapi (>=0.109.1,<0.110.0) ; extra == "api"
Requires-Dist: httpx (>=0.26.0,<0.27.0) ; extra == "api"
Requires-Dist: jinja2 (>=3.1.3,<4.0.0) ; extra == "api"
Requires-Dist: kubernetes (>=26.1.0)
Requires-Dist: kubernetes-asyncio (>=26.9.0) ; extra == "api" or extra == "airflow"
Requires-Dist: uvicorn (>=0.26.0,<0.27.0) ; extra == "api"
Requires-Dist: websockets (>=12,<13) ; extra == "api"
Project-URL: Bug Tracker, https://github.com/hussein-awala/spark-on-k8s/issues
Project-URL: Documentation, https://hussein.awala.fr/spark-on-k8s/
Project-URL: Repository, https://github.com/hussein-awala/spark-on-k8s
